blossom/__init__.py
blossom/_version.py
blossom/blossom_exe.py
blossom/dataset_io.py
blossom/default_fields.py
blossom/fields.py
blossom/organism.py
blossom/parameter_io.py
blossom/parse_intent.py
blossom/population_funcs.py
blossom/universe.py
blossom/utils.py
blossom/world.py
blossom/world_generator.py
blossom/organism_behavior/__init__.py
blossom/organism_behavior/action.py
blossom/organism_behavior/drinking.py
blossom/organism_behavior/eating.py
blossom/organism_behavior/movement.py
blossom/organism_behavior/reproduction.py
blossom/simulation/__init__.py
blossom/simulation/dataset_io.py
blossom/simulation/default_fields.py
blossom/simulation/organism.py
blossom/simulation/parameter_io.py
blossom/simulation/parse_intent.py
blossom/simulation/population_funcs.py
blossom/simulation/universe.py
blossom/simulation/utils.py
blossom/simulation/world.py
blossom/simulation/world_generator.py
blossom/simulation/organism_behavior/__init__.py
blossom/simulation/organism_behavior/action.py
blossom/simulation/organism_behavior/drinking.py
blossom/simulation/organism_behavior/eating.py
blossom/simulation/organism_behavior/movement.py
blossom/simulation/organism_behavior/reproduction.py
blossom/visualization/__init__.py
blossom/visualization/dashboard.py
blossom/visualization/parsing.py
blossom/visualization/render.py
blossom-2.0.0.dist-info/LICENSE
blossom-2.0.0.dist-info/METADATA
blossom-2.0.0.dist-info/WHEEL
blossom-2.0.0.dist-info/entry_points.txt
blossom-2.0.0.dist-info/top_level.txt
blossom-2.0.0.dist-info/RECORD
