Metadata-Version: 2.1
Name: blossom
Version: 2.0.0
Summary: A simple evolution simulator
Home-page: https://github.com/blossom-evolution/blossom
Author: Bryan Brzycki
Author-email: bbrzycki@berkeley.edu
Project-URL: Documentation, https://blossom.readthedocs.io/en/latest/
Project-URL: Source, https://github.com/blossom-evolution/blossom
Classifier: Programming Language :: Python :: 3
Classifier: License :: OSI Approved :: MIT License
Classifier: Operating System :: OS Independent
License-File: LICENSE
Requires-Dist: uuid
Requires-Dist: numpy
Requires-Dist: pandas
Requires-Dist: configparser
Requires-Dist: dash
Requires-Dist: dash-bootstrap-components
Requires-Dist: click
Requires-Dist: humanfriendly
Requires-Dist: PyYAML
Requires-Dist: matplotlib
Requires-Dist: imageio
Requires-Dist: sphinx-rtd-theme >=0.4.3
